AUTHORS
HISTORY.rst
MANIFEST.in
README.md
setup.py
CloudStackClient/BaseClient.py
CloudStackClient/Client.py
CloudStackClient/ExtendedClient.py
CloudStackClient/__init__.py
CloudStackClient.egg-info/PKG-INFO
CloudStackClient.egg-info/SOURCES.txt
CloudStackClient.egg-info/dependency_links.txt
CloudStackClient.egg-info/top_level.txt