Metadata-Version: 1.0
Name: CloudStackClient
Version: 0.1.2
Summary: CloudStack API Client
Home-page: https://github.com/terbolous/cloudstack-python-client
Author: Jason Hancock
Author-email: terbolous@gmail.com
License: MIT
Platform: Posix; MacOS X; Windows
